Workbook

Sheet Summary
A1: EMI Calculator - Test Case Summary
A2: Application: https://emicalculator.net/ | Counts update automatically from the "Test Cases" sheet (edit the Status column there).
A4: Test Type | B4: Total | C4: Automated | D4: Manual | E4: Pass | F4: Fail | G4: Blocked | H4: Not Run | I4: Pass %
A5: Functional | B5: =COUNTIF('Test Cases'!$B$2:$B$101,A5) -> 12 | C5: =COUNTIFS('Test Cases'!$B$2:$B$101,A5,'Test Cases'!$G$2:$G$101,"Automated") -> 8 | D5: =COUNTIFS('Test Cases'!$B$2:$B$101,A5,'Test Cases'!$G$2:$G$101,"Manual") -> 4 | E5: =COUNTIFS('Test Cases'!$B$2:$B$101,$A5,'Test Cases'!$J$2:$J$101,"Pass") -> 0 | F5: =COUNTIFS('Test Cases'!$B$2:$B$101,$A5,'Test Cases'!$J$2:$J$101,"Fail") -> 0 | G5: =COUNTIFS('Test Cases'!$B$2:$B$101,$A5,'Test Cases'!$J$2:$J$101,"Blocked") -> 0 | H5: =COUNTIFS('Test Cases'!$B$2:$B$101,$A5,'Test Cases'!$J$2:$J$101,"Not Run") -> 12 | I5: =IF(B5=0,0,E5/B5) -> 0
A6: Calculation Accuracy | B6: =COUNTIF('Test Cases'!$B$2:$B$101,A6) -> 18 | C6: =COUNTIFS('Test Cases'!$B$2:$B$101,A6,'Test Cases'!$G$2:$G$101,"Automated") -> 15 | D6: =COUNTIFS('Test Cases'!$B$2:$B$101,A6,'Test Cases'!$G$2:$G$101,"Manual") -> 3 | E6: =COUNTIFS('Test Cases'!$B$2:$B$101,$A6,'Test Cases'!$J$2:$J$101,"Pass") -> 0 | F6: =COUNTIFS('Test Cases'!$B$2:$B$101,$A6,'Test Cases'!$J$2:$J$101,"Fail") -> 0 | G6: =COUNTIFS('Test Cases'!$B$2:$B$101,$A6,'Test Cases'!$J$2:$J$101,"Blocked") -> 0 | H6: =COUNTIFS('Test Cases'!$B$2:$B$101,$A6,'Test Cases'!$J$2:$J$101,"Not Run") -> 18 | I6: =IF(B6=0,0,E6/B6) -> 0
A7: Data Consistency | B7: =COUNTIF('Test Cases'!$B$2:$B$101,A7) -> 20 | C7: =COUNTIFS('Test Cases'!$B$2:$B$101,A7,'Test Cases'!$G$2:$G$101,"Automated") -> 17 | D7: =COUNTIFS('Test Cases'!$B$2:$B$101,A7,'Test Cases'!$G$2:$G$101,"Manual") -> 3 | E7: =COUNTIFS('Test Cases'!$B$2:$B$101,$A7,'Test Cases'!$J$2:$J$101,"Pass") -> 0 | F7: =COUNTIFS('Test Cases'!$B$2:$B$101,$A7,'Test Cases'!$J$2:$J$101,"Fail") -> 0 | G7: =COUNTIFS('Test Cases'!$B$2:$B$101,$A7,'Test Cases'!$J$2:$J$101,"Blocked") -> 0 | H7: =COUNTIFS('Test Cases'!$B$2:$B$101,$A7,'Test Cases'!$J$2:$J$101,"Not Run") -> 20 | I7: =IF(B7=0,0,E7/B7) -> 0
A8: Boundary | B8: =COUNTIF('Test Cases'!$B$2:$B$101,A8) -> 12 | C8: =COUNTIFS('Test Cases'!$B$2:$B$101,A8,'Test Cases'!$G$2:$G$101,"Automated") -> 4 | D8: =COUNTIFS('Test Cases'!$B$2:$B$101,A8,'Test Cases'!$G$2:$G$101,"Manual") -> 8 | E8: =COUNTIFS('Test Cases'!$B$2:$B$101,$A8,'Test Cases'!$J$2:$J$101,"Pass") -> 0 | F8: =COUNTIFS('Test Cases'!$B$2:$B$101,$A8,'Test Cases'!$J$2:$J$101,"Fail") -> 0 | G8: =COUNTIFS('Test Cases'!$B$2:$B$101,$A8,'Test Cases'!$J$2:$J$101,"Blocked") -> 0 | H8: =COUNTIFS('Test Cases'!$B$2:$B$101,$A8,'Test Cases'!$J$2:$J$101,"Not Run") -> 12 | I8: =IF(B8=0,0,E8/B8) -> 0
A9: Negative / Validation | B9: =COUNTIF('Test Cases'!$B$2:$B$101,A9) -> 12 | C9: =COUNTIFS('Test Cases'!$B$2:$B$101,A9,'Test Cases'!$G$2:$G$101,"Automated") -> 7 | D9: =COUNTIFS('Test Cases'!$B$2:$B$101,A9,'Test Cases'!$G$2:$G$101,"Manual") -> 5 | E9: =COUNTIFS('Test Cases'!$B$2:$B$101,$A9,'Test Cases'!$J$2:$J$101,"Pass") -> 0 | F9: =COUNTIFS('Test Cases'!$B$2:$B$101,$A9,'Test Cases'!$J$2:$J$101,"Fail") -> 0 | G9: =COUNTIFS('Test Cases'!$B$2:$B$101,$A9,'Test Cases'!$J$2:$J$101,"Blocked") -> 0 | H9: =COUNTIFS('Test Cases'!$B$2:$B$101,$A9,'Test Cases'!$J$2:$J$101,"Not Run") -> 12 | I9: =IF(B9=0,0,E9/B9) -> 0
A10: UI / UX | B10: =COUNTIF('Test Cases'!$B$2:$B$101,A10) -> 8 | C10: =COUNTIFS('Test Cases'!$B$2:$B$101,A10,'Test Cases'!$G$2:$G$101,"Automated") -> 0 | D10: =COUNTIFS('Test Cases'!$B$2:$B$101,A10,'Test Cases'!$G$2:$G$101,"Manual") -> 8 | E10: =COUNTIFS('Test Cases'!$B$2:$B$101,$A10,'Test Cases'!$J$2:$J$101,"Pass") -> 0 | F10: =COUNTIFS('Test Cases'!$B$2:$B$101,$A10,'Test Cases'!$J$2:$J$101,"Fail") -> 0 | G10: =COUNTIFS('Test Cases'!$B$2:$B$101,$A10,'Test Cases'!$J$2:$J$101,"Blocked") -> 0 | H10: =COUNTIFS('Test Cases'!$B$2:$B$101,$A10,'Test Cases'!$J$2:$J$101,"Not Run") -> 8 | I10: =IF(B10=0,0,E10/B10) -> 0
A11: Compatibility | B11: =COUNTIF('Test Cases'!$B$2:$B$101,A11) -> 7 | C11: =COUNTIFS('Test Cases'!$B$2:$B$101,A11,'Test Cases'!$G$2:$G$101,"Automated") -> 3 | D11: =COUNTIFS('Test Cases'!$B$2:$B$101,A11,'Test Cases'!$G$2:$G$101,"Manual") -> 4 | E11: =COUNTIFS('Test Cases'!$B$2:$B$101,$A11,'Test Cases'!$J$2:$J$101,"Pass") -> 0 | F11: =COUNTIFS('Test Cases'!$B$2:$B$101,$A11,'Test Cases'!$J$2:$J$101,"Fail") -> 0 | G11: =COUNTIFS('Test Cases'!$B$2:$B$101,$A11,'Test Cases'!$J$2:$J$101,"Blocked") -> 0 | H11: =COUNTIFS('Test Cases'!$B$2:$B$101,$A11,'Test Cases'!$J$2:$J$101,"Not Run") -> 7 | I11: =IF(B11=0,0,E11/B11) -> 0
A12: Accessibility | B12: =COUNTIF('Test Cases'!$B$2:$B$101,A12) -> 5 | C12: =COUNTIFS('Test Cases'!$B$2:$B$101,A12,'Test Cases'!$G$2:$G$101,"Automated") -> 1 | D12: =COUNTIFS('Test Cases'!$B$2:$B$101,A12,'Test Cases'!$G$2:$G$101,"Manual") -> 4 | E12: =COUNTIFS('Test Cases'!$B$2:$B$101,$A12,'Test Cases'!$J$2:$J$101,"Pass") -> 0 | F12: =COUNTIFS('Test Cases'!$B$2:$B$101,$A12,'Test Cases'!$J$2:$J$101,"Fail") -> 0 | G12: =COUNTIFS('Test Cases'!$B$2:$B$101,$A12,'Test Cases'!$J$2:$J$101,"Blocked") -> 0 | H12: =COUNTIFS('Test Cases'!$B$2:$B$101,$A12,'Test Cases'!$J$2:$J$101,"Not Run") -> 5 | I12: =IF(B12=0,0,E12/B12) -> 0
A13: Performance | B13: =COUNTIF('Test Cases'!$B$2:$B$101,A13) -> 3 | C13: =COUNTIFS('Test Cases'!$B$2:$B$101,A13,'Test Cases'!$G$2:$G$101,"Automated") -> 0 | D13: =COUNTIFS('Test Cases'!$B$2:$B$101,A13,'Test Cases'!$G$2:$G$101,"Manual") -> 3 | E13: =COUNTIFS('Test Cases'!$B$2:$B$101,$A13,'Test Cases'!$J$2:$J$101,"Pass") -> 0 | F13: =COUNTIFS('Test Cases'!$B$2:$B$101,$A13,'Test Cases'!$J$2:$J$101,"Fail") -> 0 | G13: =COUNTIFS('Test Cases'!$B$2:$B$101,$A13,'Test Cases'!$J$2:$J$101,"Blocked") -> 0 | H13: =COUNTIFS('Test Cases'!$B$2:$B$101,$A13,'Test Cases'!$J$2:$J$101,"Not Run") -> 3 | I13: =IF(B13=0,0,E13/B13) -> 0
A14: Security | B14: =COUNTIF('Test Cases'!$B$2:$B$101,A14) -> 3 | C14: =COUNTIFS('Test Cases'!$B$2:$B$101,A14,'Test Cases'!$G$2:$G$101,"Automated") -> 0 | D14: =COUNTIFS('Test Cases'!$B$2:$B$101,A14,'Test Cases'!$G$2:$G$101,"Manual") -> 3 | E14: =COUNTIFS('Test Cases'!$B$2:$B$101,$A14,'Test Cases'!$J$2:$J$101,"Pass") -> 0 | F14: =COUNTIFS('Test Cases'!$B$2:$B$101,$A14,'Test Cases'!$J$2:$J$101,"Fail") -> 0 | G14: =COUNTIFS('Test Cases'!$B$2:$B$101,$A14,'Test Cases'!$J$2:$J$101,"Blocked") -> 0 | H14: =COUNTIFS('Test Cases'!$B$2:$B$101,$A14,'Test Cases'!$J$2:$J$101,"Not Run") -> 3 | I14: =IF(B14=0,0,E14/B14) -> 0
A15: TOTAL | B15: =SUM(B5:B14) -> 100 | C15: =SUM(C5:C14) -> 55 | D15: =SUM(D5:D14) -> 45 | E15: =SUM(E5:E14) -> 0 | F15: =SUM(F5:F14) -> 0 | G15: =SUM(G5:G14) -> 0 | H15: =SUM(H5:H14) -> 100 | I15: =IF(B15=0,0,E15/B15) -> 0
A18: By Priority
A19: Priority | B19: Total | C19: Pass | D19: Fail | E19: Not Run
A20: P0 | B20: =COUNTIF('Test Cases'!$F$2:$F$101,A20) -> 35 | C20: =COUNTIFS('Test Cases'!$F$2:$F$101,$A20,'Test Cases'!$J$2:$J$101,"Pass") -> 0 | D20: =COUNTIFS('Test Cases'!$F$2:$F$101,$A20,'Test Cases'!$J$2:$J$101,"Fail") -> 0 | E20: =COUNTIFS('Test Cases'!$F$2:$F$101,$A20,'Test Cases'!$J$2:$J$101,"Not Run") -> 35
A21: P1 | B21: =COUNTIF('Test Cases'!$F$2:$F$101,A21) -> 42 | C21: =COUNTIFS('Test Cases'!$F$2:$F$101,$A21,'Test Cases'!$J$2:$J$101,"Pass") -> 0 | D21: =COUNTIFS('Test Cases'!$F$2:$F$101,$A21,'Test Cases'!$J$2:$J$101,"Fail") -> 0 | E21: =COUNTIFS('Test Cases'!$F$2:$F$101,$A21,'Test Cases'!$J$2:$J$101,"Not Run") -> 42
A22: P2 | B22: =COUNTIF('Test Cases'!$F$2:$F$101,A22) -> 20 | C22: =COUNTIFS('Test Cases'!$F$2:$F$101,$A22,'Test Cases'!$J$2:$J$101,"Pass") -> 0 | D22: =COUNTIFS('Test Cases'!$F$2:$F$101,$A22,'Test Cases'!$J$2:$J$101,"Fail") -> 0 | E22: =COUNTIFS('Test Cases'!$F$2:$F$101,$A22,'Test Cases'!$J$2:$J$101,"Not Run") -> 20
A23: P3 | B23: =COUNTIF('Test Cases'!$F$2:$F$101,A23) -> 3 | C23: =COUNTIFS('Test Cases'!$F$2:$F$101,$A23,'Test Cases'!$J$2:$J$101,"Pass") -> 0 | D23: =COUNTIFS('Test Cases'!$F$2:$F$101,$A23,'Test Cases'!$J$2:$J$101,"Fail") -> 0 | E23: =COUNTIFS('Test Cases'!$F$2:$F$101,$A23,'Test Cases'!$J$2:$J$101,"Not Run") -> 3
A26: How to use
A27: 1. Go to the "Test Cases" sheet and set Status (dropdown) after each execution; fill Actual Result, Tester, Date.
A28: 2. Raise a defect using docs/03_BUG_REPORTS template and put its ID in "Defect ID / Notes".
A29: 3. Execution Mode: "Automated" cases map to the Playwright file in the "Automation File" column; "Manual" cases are run by hand.
A30: 4. Priority: P0 critical, P1 high, P2 medium, P3 low.
A31: Baseline for expected values unless stated: Rs 50,00,000 / 9 % / 20 years -> EMI 44,986 (see Test Plan section 8 for tolerances).

Sheet Test Cases
A1: Test Case ID | B1: Test Type | C1: Title | D1: Steps / Input | E1: Expected Result | F1: Priority | G1: Execution Mode | H1: Automation File | I1: Actual Result | J1: Status | K1: Tester | L1: Date | M1: Defect ID / Notes
A2: FUN-01 | B2: Functional | C2: Default values on load | D2: Open site | E2: Amount 50,00,000; Rate 9; Tenure 20 Yr; EMI 44,986; Interest 57,96,711; Total 1,07,96,711 | F2: P0 | G2: Automated | H2: tests/ui/emi-calculation.spec.ts | J2: Not Run
A3: FUN-02 | B3: Functional | C3: Amount slider updates text box and results | D3: Drag amount handle right | E3: Text box value increases; EMI increases | F3: P0 | G3: Automated | H3: tests/ui/emi-calculation.spec.ts | J3: Not Run
A4: FUN-03 | B4: Functional | C4: Rate slider updates text box and results | D4: Drag rate handle | E4: Box value changes within 5-20; EMI changes | F4: P0 | G4: Automated | H4: tests/ui/emi-calculation.spec.ts | J4: Not Run
A5: FUN-04 | B5: Functional | C5: Tenure slider updates text box and results | D5: Drag tenure handle | E5: Box within 0-30; EMI changes | F5: P0 | G5: Automated | H5: tests/ui/emi-calculation.spec.ts | J5: Not Run
A6: FUN-05 | B6: Functional | C6: Text box updates slider position | D6: Type 1,00,00,000 in amount | E6: Handle moves to ~100L tick; results refresh | F6: P1 | G6: Manual | J6: Not Run
A7: FUN-06 | B7: Functional | C7: Typed values recalc on blur/Enter | D7: Type amount, press Tab / Enter | E7: Results refresh once | F7: P0 | G7: Automated | H7: tests/ui/emi-calculation.spec.ts | J7: Not Run
A8: FUN-07 | B8: Functional | C8: Yr -> Mo toggle keeps loan equivalent | D8: Switch to Mo, type 240 | E8: EMI identical to 20 Yr | F8: P0 | G8: Automated | H8: tests/ui/emi-calculation.spec.ts | J8: Not Run
A9: FUN-08 | B9: Functional | C9: Mo -> Yr toggle conversion | D9: In Mo mode with 240, click Yr | E9: Box shows 20 (or equivalent), EMI unchanged | F9: P1 | G9: Manual | J9: Not Run
A10: FUN-09 | B10: Functional | C10: Slider keyboard control | D10: Focus handle, press Right x3 | E10: Value increases per step | F10: P1 | G10: Automated | H10: tests/ui/emi-calculation.spec.ts | J10: Not Run
A11: FUN-10 | B11: Functional | C11: Tab switch Home/Personal/Car | D11: Click each tab | E11: Defaults of that loan type load; calc works | F11: P2 | G11: Manual | J11: Not Run
A12: FUN-11 | B12: Functional | C12: Reload resets state | D12: Change values, reload | E12: Defaults restored | F12: P2 | G12: Manual | J12: Not Run
A13: FUN-12 | B13: Functional | C13: Combined change of all three inputs | D13: Change all three, observe once | E13: One consistent final state (no stale mix) | F13: P1 | G13: Automated | H13: tests/ui/emi-calculation.spec.ts | J13: Not Run
A14: CAL-01 | B14: Calculation Accuracy | C14: Baseline | D14: P / rate / years = 50L / 9 / 20 | E14: 44,986 | F14: P0 | G14: Automated | H14: tests/ui/emi-calculation.spec.ts | J14: Not Run
A15: CAL-02 | B15: Calculation Accuracy | C15: Mid-range slider scenario | D15: P / rate / years = 75L / 8.5 / 15 | E15: formula | F15: P0 | G15: Automated | H15: tests/ui/emi-calculation.spec.ts | J15: Not Run
A16: CAL-03 | B16: Calculation Accuracy | C16: Large long loan | D16: P / rate / years = 1.5Cr / 11 / 30 | E16: formula | F16: P0 | G16: Automated | H16: tests/ui/emi-calculation.spec.ts | J16: Not Run
A17: CAL-04 | B17: Calculation Accuracy | C17: Small short loan | D17: P / rate / years = 10L / 7 / 5 | E17: formula | F17: P0 | G17: Automated | H17: tests/ui/emi-calculation.spec.ts | J17: Not Run
A18: CAL-05 | B18: Calculation Accuracy | C18: High rate | D18: P / rate / years = 50L / 18 / 10 | E18: formula | F18: P1 | G18: Automated | H18: tests/ui/emi-calculation.spec.ts | J18: Not Run
A19: CAL-06 | B19: Calculation Accuracy | C19: Near upper bounds | D19: P / rate / years = 1.95Cr / 19.5 / 29 | E19: formula | F19: P1 | G19: Automated | H19: tests/ui/emi-calculation.spec.ts | J19: Not Run
A20: CAL-07 | B20: Calculation Accuracy | C20: Near lower bounds | D20: P / rate / years = 5L / 5.5 / 1 | E20: formula | F20: P1 | G20: Automated | H20: tests/ui/emi-calculation.spec.ts | J20: Not Run
A21: CAL-08 | B21: Calculation Accuracy | C21: Typed fractional rate | D21: P / rate / years = 25L / 6.75 / 12 | E21: formula | F21: P1 | G21: Automated | H21: tests/ui/emi-calculation.spec.ts | J21: Not Run
A22: CAL-09 | B22: Calculation Accuracy | C22: Months mode odd tenure | D22: P / rate / years = 50L / 9 / 18 months | E22: formula | F22: P1 | G22: Automated | H22: tests/ui/emi-calculation.spec.ts | J22: Not Run
A23: CAL-10 | B23: Calculation Accuracy | C23: Total interest = EMI x n - P | D23: any | E23: within n x 0.5 + 1 | F23: P0 | G23: Automated | H23: tests/ui/emi-calculation.spec.ts | J23: Not Run
A24: CAL-11 | B24: Calculation Accuracy | C24: Total payment = P + interest | D24: any | E24: exact within 5 | F24: P0 | G24: Automated | H24: tests/ui/emi-calculation.spec.ts | J24: Not Run
... A26: CAL-13 | B26: Calculation Accuracy | C26: Monotonicity: tenure up -> EMI down, total interest up | D26: P / rate / years = 20 -> 25 | E26: as stated | F26: P1 | G26: Automated | H26: tests/unit/emi-oracle.spec.ts | J26: Not Run
A27: CAL-14 | B27: Calculation Accuracy | C27: Monotonicity: amount up -> EMI up (linear) | D27: P / rate / years = 50L -> 100L | E27: EMI doubles +/-1 | F27: P1 | G27: Manual | J27: Not Run
A28: CAL-15 | B28: Calculation Accuracy | C28: Zero interest edge | D28: P / rate / years = rate 0 | E28: EMI = P/n (if accepted) | F28: P1 | G28: Manual | J28: Not Run
A29: CAL-16 | B29: Calculation Accuracy | C29: 1-month tenure | D29: P / rate / years = n = 1 | E29: EMI = P(1+r) | F29: P1 | G29: Manual | J29: Not Run
A30: CAL-17 | B30: Calculation Accuracy | C30: Oracle self-test vs spec screenshot | D30: - | E30: matches every printed figure | F30: P0 | G30: Automated | H30: tests/unit/emi-oracle.spec.ts | J30: Not Run
A31: CAL-18 | B31: Calculation Accuracy | C31: Pie split | D31: P / rate / years = 50L/9/20 | E31: 46.3 % principal, 53.7 % interest | F31: P1 | G31: Automated | H31: tests/ui/emi-calculation.spec.ts | J31: Not Run
A32: DAT-01 | B32: Data Consistency | C32: Table row = formula, year by year (P, I, Total, Balance, Paid %) | E32: within tolerances (Plan section 8) | F32: P0 | G32: Automated | H32: tests/ui/schedule-and-chart.spec.ts | J32: Not Run
A33: DAT-02 | B33: Data Consistency | C33: Principal + Interest = Total for every row | E33: +/- 2 | F33: P0 | G33: Automated | H33: tests/ui/schedule-and-chart.spec.ts | J33: Not Run
A34: DAT-03 | B34: Data Consistency | C34: Balance non-increasing; last balance = 0 | E34: exact | F34: P0 | G34: Automated | H34: tests/ui/schedule-and-chart.spec.ts | J34: Not Run
A35: DAT-04 | B35: Data Consistency | C35: Sum of yearly principal = loan amount | E35: +/- 1.5 x rows | F35: P0 | G35: Automated | H35: tests/ui/schedule-and-chart.spec.ts | J35: Not Run
A36: DAT-05 | B36: Data Consistency | C36: Loan Paid % last row = 100.00 % and rises monotonically | E36: exact | F36: P1 | G36: Automated | H36: tests/ui/schedule-and-chart.spec.ts | J36: Not Run
A37: DAT-06 | B37: Data Consistency | C37: First/last year are partial (11 and 1 instalments in sample) | E37: derived from UI | F37: P1 | G37: Automated | H37: tests/ui/schedule-and-chart.spec.ts | J37: Not Run
A38: DAT-07 | B38: Data Consistency | C38: Bar chart principal/interest/balance = table, per year | E38: +/- 1 | F38: P0 | G38: Automated | H38: tests/ui/schedule-and-chart.spec.ts | J38: Not Run
A39: DAT-08 | B39: Data Consistency | C39: Chart has one point per table row | E39: equal counts | F39: P1 | G39: Automated | H39: tests/ui/schedule-and-chart.spec.ts | J39: Not Run
A40: DAT-09 | B40: Data Consistency | C40: Chart/table refresh after input change (no stale data) | E40: updated | F40: P0 | G40: Automated | H40: tests/ui/schedule-and-chart.spec.ts | J40: Not Run
A41: DAT-10 | B41: Data Consistency | C41: Pie % = interest/total and principal/total, sum 100 | E41: +/- 0.5 | F41: P1 | G41: Automated | H41: tests/ui/schedule-and-chart.spec.ts | J41: Not Run
A42: DAT-11 | B42: Data Consistency | C42: Cards vs table: total interest = sum yearly interest | E42: +/- rows | F42: P0 | G42: Automated | H42: tests/ui/schedule-and-chart.spec.ts | J42: Not Run
A43: DAT-12 | B43: Data Consistency | C43: Expand a year (the + icon) -> months sum to the year row | E43: exact +/- 1 | F43: P1 | G43: Manual | J43: Not Run
A44: DAT-13 | B44: Data Consistency | C44: Excel downloads, valid .xlsx, non-empty | E44: PK header, size > 2 KB | F44: P0 | G44: Automated | H44: tests/ui/excel-download.spec.ts | J44: Not Run
A45: DAT-14 | B45: Data Consistency | C45: Excel sum(principal) = loan amount | E45: +/- rows | F45: P0 | G45: Automated | H45: tests/ui/excel-download.spec.ts | J45: Not Run
A46: DAT-15 | B46: Data Consistency | C46: Excel sum(interest) = UI total interest and formula | E46: +/- rows | F46: P0 | G46: Automated | H46: tests/ui/excel-download.spec.ts | J46: Not Run
A47: DAT-16 | B47: Data Consistency | C47: Excel closing balance = 0, balance never increases | E47: yes | F47: P0 | G47: Automated | H47: tests/ui/excel-download.spec.ts | J47: Not Run
A48: DAT-17 | B48: Data Consistency | C48: Excel monthly rows: P + I = EMI (if monthly layout) | E48: +/- 2 | F48: P1 | G48: Automated | H48: tests/ui/excel-download.spec.ts | J48: Not Run
A49: DAT-18 | B49: Data Consistency | C49: Excel rows equal UI table (if yearly layout) | E49: +/- 1 | F49: P1 | G49: Automated | H49: tests/ui/excel-download.spec.ts | J49: Not Run
A50: DAT-19 | B50: Data Consistency | C50: Excel reflects *changed* inputs, not defaults | E50: values differ from baseline | F50: P1 | G50: Manual | J50: Not Run
A51: DAT-20 | B51: Data Consistency | C51: Number formatting in Excel (currency, no text-numbers) | E51: cells numeric | F51: P2 | G51: Manual | J51: Not Run
A52: BVA-01 | B52: Boundary | C52: Amount = 0 | D52: Set Amount to 0 | E52: No crash; no NaN; sensible message or zero EMI | F52: P1 | G52: Automated | H52: tests/ui/emi-calculation.spec.ts (@negative) | J52: Not Run
A53: BVA-02 | B53: Boundary | C53: Amount = 1 | D53: Set Amount to 1 | E53: Handled | F53: P2 | G53: Manual | J53: Not Run
A54: BVA-03 | B54: Boundary | C54: Amount = 2,00,00,000 (max) | D54: Set Amount to 2,00,00,000 (max) | E54: Exact formula EMI | F54: P0 | G54: Automated | H54: tests/ui/emi-calculation.spec.ts (@negative) | J54: Not Run
A55: BVA-04 | B55: Boundary | C55: Amount = 2,00,00,001 (max+1) | D55: Set Amount to 2,00,00,001 (max+1) | E55: Clamped or rejected, not silently wrong | F55: P1 | G55: Manual | J55: Not Run
A56: BVA-05 | B56: Boundary | C56: Rate = 5 (min) | D56: Set Rate to 5 (min) | E56: Formula | F56: P0 | G56: Manual | J56: Not Run
A57: BVA-06 | B57: Boundary | C57: Rate = 20 (max) | D57: Set Rate to 20 (max) | E57: Formula | F57: P0 | G57: Manual | J57: Not Run
A58: BVA-07 | B58: Boundary | C58: Rate = 4.99 / 20.01 | D58: Set Rate to 4.99 / 20.01 | E58: Clamp/reject | F58: P1 | G58: Manual | J58: Not Run
A59: BVA-08 | B59: Boundary | C59: Rate = 0 | D59: Set Rate to 0 | E59: No NaN / div-by-zero | F59: P0 | G59: Automated | H59: tests/ui/emi-calculation.spec.ts (@negative) | J59: Not Run
A60: BVA-09 | B60: Boundary | C60: Tenure = 0 | D60: Set Tenure to 0 | E60: No Infinity | F60: P0 | G60: Automated | H60: tests/ui/emi-calculation.spec.ts (@negative) | J60: Not Run
A61: BVA-10 | B61: Boundary | C61: Tenure = 1 month | D61: Set Tenure to 1 month | E61: Formula | F61: P1 | G61: Manual | J61: Not Run
A62: BVA-11 | B62: Boundary | C62: Tenure = 30 years (max) / 360 months | D62: Set Tenure to 30 years (max) / 360 months | E62: Formula, 31 table rows | F62: P0 | G62: Manual | J62: Not Run
A63: BVA-12 | B63: Boundary | C63: Tenure = 31 years / 361 months | D63: Set Tenure to 31 years / 361 months | E63: Clamp/reject | F63: P1 | G63: Manual | J63: Not Run
A64: NEG-01 | B64: Negative / Validation | C64: Input: Letters in amount ("abcd") | D64: Enter Letters in amount ("abcd") | E64: No NaN; value rejected or reverted | F64: P0 | G64: Automated | H64: tests/ui/emi-calculation.spec.ts (@negative) | J64: Not Run
A65: NEG-02 | B65: Negative / Validation | C65: Input: Negative amount | D65: Enter Negative amount | E65: Rejected / not negative output | F65: P0 | G65: Automated | H65: tests/ui/emi-calculation.spec.ts (@negative) | J65: Not Run
A66: NEG-03 | B66: Negative / Validation | C66: Input: Huge amount (999999999999) | D66: Enter Huge amount (999999999999) | E66: No overflow, no broken layout | F66: P1 | G66: Automated | H66: tests/ui/emi-calculation.spec.ts (@negative) | J66: Not Run
A67: NEG-04 | B67: Negative / Validation | C67: Input: Negative rate | D67: Enter Negative rate | E67: Rejected | F67: P1 | G67: Automated | H67: tests/ui/emi-calculation.spec.ts (@negative) | J67: Not Run
A68: NEG-05 | B68: Negative / Validation | C68: Input: Rate 99 | D68: Enter Rate 99 | E68: Clamped / rejected | F68: P1 | G68: Automated | H68: tests/ui/emi-calculation.spec.ts (@negative) | J68: Not Run
A69: NEG-06 | B69: Negative / Validation | C69: Input: Many decimals in rate (9.999999) | D69: Enter Many decimals in rate (9.999999) | E69: Handled, display formatted | F69: P2 | G69: Automated | H69: tests/ui/emi-calculation.spec.ts (@negative) | J69: Not Run
A70: NEG-07 | B70: Negative / Validation | C70: Input: Negative / > max tenure | D70: Enter Negative / > max tenure | E70: Rejected | F70: P1 | G70: Automated | H70: tests/ui/emi-calculation.spec.ts (@negative) | J70: Not Run
A71: NEG-08 | B71: Negative / Validation | C71: Input: Empty field then blur | D71: Enter Empty field then blur | E71: No NaN; restore last valid | F71: P0 | G71: Manual | J71: Not Run
A72: NEG-09 | B72: Negative / Validation | C72: Input: Paste "50,00,000" / "5000000.50" / " 5000000 " | D72: Enter Paste "50,00,000" / "5000000.50" / " 5000000 " | E72: Parsed or rejected cleanly | F72: P1 | G72: Manual | J72: Not Run
A73: NEG-10 | B73: Negative / Validation | C73: Input: Special chars / emoji / script tag | D73: Enter Special chars / emoji / script tag | E73: No XSS, no JS error | F73: P1 | G73: Manual | J73: Not Run
A74: NEG-11 | B74: Negative / Validation | C74: Input: Rapid repeated input (type 20 changes quickly) | D74: Enter Rapid repeated input (type 20 changes quickly) | E74: Final state consistent | F74: P2 | G74: Manual | J74: Not Run
A75: NEG-12 | B75: Negative / Validation | C75: Input: Leading zeros "0005000000" | D75: Enter Leading zeros "0005000000" | E75: Interpreted as 5,000,000 | F75: P2 | G75: Manual | J75: Not Run
A76: UI-01 | B76: UI / UX | C76: Indian digit grouping (xx,xx,xxx) on all rupee values | E76: consistent | F76: P1 | G76: Manual | J76: Not Run
A77: UI-02 | B77: UI / UX | C77: Rupee symbol present on cards, chart axes, table | E77: present | F77: P2 | G77: Manual | J77: Not Run
A78: UI-03 | B78: UI / UX | C78: Slider tick labels (0, 25L ... 200L) correct | E78: match range | F78: P2 | G78: Manual | J78: Not Run
A79: UI-04 | B79: UI / UX | C79: Handle position reflects value | E79: within one tick | F79: P2 | G79: Manual | J79: Not Run
A80: UI-05 | B80: UI / UX | C80: Chart legend/tooltip content correct | E80: per-year values match table | F80: P1 | G80: Manual | J80: Not Run
A81: UI-06 | B81: UI / UX | C81: Table header colours/labels (Principal (A), Interest (B), A+B) | E81: match spec | F81: P2 | G81: Manual | J81: Not Run
A82: UI-07 | B82: UI / UX | C82: No text overflow with max values (Rs 2Cr, 30y) | E82: none | F82: P2 | G82: Manual | J82: Not Run
A83: UI-08 | B83: UI / UX | C83: Hover on pie slice shows value | E83: shown | F83: P3 | G83: Manual | J83: Not Run
A84: CMP-01 | B84: Compatibility | C84: Chrome desktop smoke | E84: pass | F84: P0 | G84: Automated | H84: playwright.config.ts projects | J84: Not Run
A85: CMP-02 | B85: Compatibility | C85: Firefox desktop smoke | E85: pass | F85: P0 | G85: Automated | H85: playwright.config.ts projects | J85: Not Run
A86: CMP-03 | B86: Compatibility | C86: Mobile Chrome (Pixel 7) smoke | E86: pass | F86: P1 | G86: Automated | H86: playwright.config.ts projects | J86: Not Run
A87: CMP-04 | B87: Compatibility | C87: Safari macOS / iOS smoke | E87: pass | F87: P1 | G87: Manual | J87: Not Run
A88: CMP-05 | B88: Compatibility | C88: Edge smoke | E88: pass | F88: P2 | G88: Manual | J88: Not Run
A89: CMP-06 | B89: Compatibility | C89: 320 px width, landscape rotation | E89: no horizontal clipping; sliders draggable by touch | F89: P1 | G89: Manual | J89: Not Run
A90: CMP-07 | B90: Compatibility | C90: 200 % browser zoom | E90: usable | F90: P2 | G90: Manual | J90: Not Run
A91: ACC-01 | B91: Accessibility | C91: Sliders operable by keyboard | E91: arrows/Home/End change value | F91: P1 | G91: Automated | H91: tests/ui/emi-calculation.spec.ts | J91: Not Run
A92: ACC-02 | B92: Accessibility | C92: Tab order logical; visible focus | E92: yes | F92: P1 | G92: Manual | J92: Not Run
A93: ACC-03 | B93: Accessibility | C93: Inputs have labels / accessible names | E93: yes | F93: P2 | G93: Manual | J93: Not Run
A94: ACC-04 | B94: Accessibility | C94: Colour contrast of orange on white (table/legend) | E94: >= 4.5:1 for text | F94: P2 | G94: Manual | J94: Not Run
A95: ACC-05 | B95: Accessibility | C95: Chart has text alternative or table equivalent | E95: table exists | F95: P3 | G95: Manual | J95: Not Run
A96: PRF-01 | B96: Performance | C96: First meaningful render of EMI | E96: < 3 s on broadband | F96: P2 | G96: Manual | J96: Not Run
A97: PRF-02 | B97: Performance | C97: Recalc latency while dragging | E97: < 200 ms, no jank | F97: P2 | G97: Manual | J97: Not Run
A98: PRF-03 | B98: Performance | C98: Re-render at 360-row month expansion | E98: < 1 s | F98: P3 | G98: Manual | J98: Not Run
A99: SEC-01 | B99: Security | C99: XSS payload in inputs not executed | E99: no alert, escaped | F99: P1 | G99: Manual | J99: Not Run
A100: SEC-02 | B100: Security | C100: HTTPS enforced, no mixed content | E100: yes | F100: P2 | G100: Manual | J100: Not Run
A101: SEC-03 | B101: Security | C101: Excel has no formula-injection / macros | E101: static values | F101: P2 | G101: Manual | J101: Not Run

Sheet EMI Reference
A1: EMI formula reference (live calculator - edit the blue cells)
A3: Loan amount (Rs) | B3: 5000000
A4: Annual interest rate (%) | B4: 9
A5: Tenure (years) | B5: 20
A7: Monthly rate r | B7: =B4/12/100 -> 0.0075
A8: Months n | B8: =B5*12 -> 240
A9: EMI | B9: =IF(B7=0,B3/B8,B3*B7*(1+B7)^B8/((1+B7)^B8-1)) -> 44986.298
A10: Total payment | B10: =B9*B8 -> 10796711
A11: Total interest | B11: =B10-B3 -> 5796711.5
A12: Interest share of total payment | B12: =IF(B10=0,0,B11/B10) -> 0.53689602
A14: Formula: EMI = P*r*(1+r)^n / ((1+r)^n - 1). Expected for defaults: EMI 44,986 | interest 57,96,711 | total 1,07,96,711 | split 46.3% / 53.7%.
A15: Yellow cells are inputs (hardcoded by design). Rupee figures use plain thousands separators here; the site uses Indian grouping.
